nistats/__init__.py
nistats/conftest.py
nistats/contrasts.py
nistats/datasets.py
nistats/design_matrix.py
nistats/experimental_paradigm.py
nistats/first_level_model.py
nistats/hemodynamic_models.py
nistats/model.py
nistats/regression.py
nistats/second_level_model.py
nistats/thresholding.py
nistats/utils.py
nistats/version.py
nistats/_utils/__init__.py
nistats/_utils/datasets.py
nistats/_utils/helpers.py
nistats/_utils/testing.py
nistats/reporting/__init__.py
nistats/reporting/_compare_niimgs.py
nistats/reporting/_get_clusters_table.py
nistats/reporting/_plot_matrices.py
nistats/reporting/glm_reporter.py
nistats/reporting/sphinx_report.py
nistats/reporting/glm_reporter_templates/__init__.py
nistats/reporting/glm_reporter_templates/contrast_template.html
nistats/reporting/glm_reporter_templates/design_matrix_template.html
nistats/reporting/glm_reporter_templates/report_template.html
nistats/reporting/glm_reporter_templates/stat_maps_contrast_clusters_template.html
nistats/tests/__init__.py
nistats/tests/spm_dmtx.npz
nistats/tests/test_check_events_file_uses_tab_separators.py
nistats/tests/test_contrasts.py
nistats/tests/test_datasets.py
nistats/tests/test_dmtx.py
nistats/tests/test_first_level_model.py
nistats/tests/test_glm_reporter.py
nistats/tests/test_helpers.py
nistats/tests/test_hemodynamic_models.py
nistats/tests/test_init.py
nistats/tests/test_model.py
nistats/tests/test_paradigm.py
nistats/tests/test_regression.py
nistats/tests/test_reporting.py
nistats/tests/test_second_level_model.py
nistats/tests/test_sphinx_report.py
nistats/tests/test_thresholding.py
nistats/tests/test_utils.py
nistats-0.0.1b2.dist-info/AUTHORS.rst
nistats-0.0.1b2.dist-info/LICENSE
nistats-0.0.1b2.dist-info/METADATA
nistats-0.0.1b2.dist-info/WHEEL
nistats-0.0.1b2.dist-info/top_level.txt
nistats-0.0.1b2.dist-info/RECORD
