Metadata-Version: 2.1
Name: nistats
Version: 0.0.1b2
Summary: Modeling and Statistical analysis of fMRI data in Python
Home-page: http://nistats.github.io
Maintainer: Bertrand Thirion
Maintainer-email: bertrand.thirion@inria.fr
License: new BSD
Download-URL: http://nistats.github.io
Platform: UNKNOWN
Classifier: Intended Audience :: Science/Research
Classifier: Intended Audience :: Developers
Classifier: License :: OSI Approved
Classifier: Programming Language :: C
Classifier: Programming Language :: Python
Classifier: Topic :: Software Development
Classifier: Topic :: Scientific/Engineering
Classifier: Operating System :: Microsoft :: Windows
Classifier: Operating System :: POSIX
Classifier: Operating System :: Unix
Classifier: Operating System :: MacOS
Classifier: Programming Language :: Python :: 2
Classifier: Programming Language :: Python :: 2.7
Classifier: Programming Language :: Python :: 3.3
Classifier: Programming Language :: Python :: 3.4
Requires-Dist: numpy (>=1.11)
Requires-Dist: scipy (>=0.17)
Requires-Dist: scikit-learn (>=0.18)
Requires-Dist: nibabel (>=2.0.2)
Requires-Dist: nilearn (>=0.4)
Requires-Dist: pandas (>=0.18.0)
